MANIFEST.in
README.rst
setup.py
django_easy_select2.egg-info/PKG-INFO
django_easy_select2.egg-info/SOURCES.txt
django_easy_select2.egg-info/dependency_links.txt
django_easy_select2.egg-info/not-zip-safe
django_easy_select2.egg-info/top_level.txt
easy_select2/__init__.py
easy_select2/admin.py
easy_select2/forms.py
easy_select2/models.py
easy_select2/utils.py
easy_select2/widgets.py
easy_select2/__pycache__/__init__.cpython-36.pyc
easy_select2/__pycache__/admin.cpython-36.pyc
easy_select2/__pycache__/forms.cpython-36.pyc
easy_select2/__pycache__/models.cpython-36.pyc
easy_select2/__pycache__/utils.cpython-36.pyc
easy_select2/__pycache__/widgets.cpython-36.pyc
easy_select2/static/easy_select2/css/easy_select2.css
easy_select2/static/easy_select2/js/easy_select2.js
easy_select2/static/easy_select2/js/init.js
easy_select2/static/easy_select2/vendor/jquery/jquery.min.js
easy_select2/static/easy_select2/vendor/jquery/jquery.min.map
easy_select2/static/easy_select2/vendor/select2/css/select2.css
easy_select2/static/easy_select2/vendor/select2/css/select2.min.css
easy_select2/static/easy_select2/vendor/select2/js/select2.full.js
easy_select2/static/easy_select2/vendor/select2/js/select2.full.min.js
easy_select2/static/easy_select2/vendor/select2/js/select2.js
easy_select2/static/easy_select2/vendor/select2/js/select2.min.js
easy_select2/static/easy_select2/vendor/select2/js/i18n/az.js
easy_select2/static/easy_select2/vendor/select2/js/i18n/bg.js
easy_select2/static/easy_select2/vendor/select2/js/i18n/ca.js
easy_select2/static/easy_select2/vendor/select2/js/i18n/cs.js
easy_select2/static/easy_select2/vendor/select2/js/i18n/da.js
easy_select2/static/easy_select2/vendor/select2/js/i18n/de.js
easy_select2/static/easy_select2/vendor/select2/js/i18n/en.js
easy_select2/static/easy_select2/vendor/select2/js/i18n/es.js
easy_select2/static/easy_select2/vendor/select2/js/i18n/et.js
easy_select2/static/easy_select2/vendor/select2/js/i18n/eu.js
easy_select2/static/easy_select2/vendor/select2/js/i18n/fa.js
easy_select2/static/easy_select2/vendor/select2/js/i18n/fi.js
easy_select2/static/easy_select2/vendor/select2/js/i18n/fr.js
easy_select2/static/easy_select2/vendor/select2/js/i18n/gl.js
