Metadata-Version: 1.1
Name: django-easy-select2
Version: 1.5.6
Summary: Django select2 theme for select input widgets.
Home-page: https://github.com/asyncee/django-easy-select2
Author: asyncee
Author-email: UNKNOWN
License: MIT
Download-URL: https://pypi.python.org/pypi/django-easy-select2/
Keywords: django select2
Platform: UNKNOWN
Classifier: Development Status :: 5 - Production/Stable
Classifier: Environment :: Web Environment
Classifier: Framework :: Django
Classifier: Intended Audience :: Developers
Classifier: License :: OSI Approved :: MIT License
Classifier: Programming Language :: Python
Classifier: Programming Language :: Python :: 3
Classifier: Programming Language :: Python :: 3.4
Classifier: Programming Language :: Python :: 3.5
Classifier: Programming Language :: Python :: 3.6
Classifier: Topic :: Software Development :: Widget Sets
